invertcolor/__init__.py
invertcolor/core.py
invertcolor-0.1.0.dist-info/licenses/LICENSE
invertcolor-0.1.0.dist-info/METADATA
invertcolor-0.1.0.dist-info/WHEEL
invertcolor-0.1.0.dist-info/top_level.txt
invertcolor-0.1.0.dist-info/RECORD
