Metadata-Version: 2.4
Name: invertcolor
Version: 0.1.0
Summary: A simple library to invert RGB colors.
Author-email: Iliyan Georgiev <georgiev.iliyan09@gmail.com>
Project-URL: Homepage, https://github.com/GeorgievIliyan/rgb_color_inverter
Classifier: Programming Language :: Python :: 3
Classifier: License :: OSI Approved :: MIT License
Classifier: Operating System :: OS Independent
Requires-Python: >=3.7
License-File: LICENSE
Dynamic: license-file
